{"nodes": [{"id": "api_check_status", "label": "GET /api/admin/check-status", "file_type": "api_endpoint", "source_file": "brain/04-api/admin/check-status/route.md", "source_location": null}, {"id": "module_error_reporting", "label": "Error Reporting Module", "file_type": "module", "source_file": "brain/04-api/admin/check-status/route.md", "source_location": null}], "edges": [{"source": "api_check_status", "target": "module_error_reporting", "relation": "conceptually_related_to", "confidence": "EXTRACTED", "confidence_score": 1.0, "source_file": "brain/04-api/admin/check-status/route.md", "weight": 1.0}], "hyperedges": []}