{"nodes": [{"id": "d_proyect_opttius_app_src_lib_ai_knowledge_readme_md", "label": "README.md", "file_type": "document", "source_file": "src/lib/ai/knowledge/README.md", "source_location": "L1"}, {"id": "knowledge_readme_ai_knowledge_base_index", "label": "AI Knowledge Base Index", "file_type": "document", "source_file": "src/lib/ai/knowledge/README.md", "source_location": "L1"}, {"id": "knowledge_readme_structure_overview", "label": "Structure Overview", "file_type": "document", "source_file": "src/lib/ai/knowledge/README.md", "source_location": "L5"}, {"id": "knowledge_readme_documentation_standards", "label": "Documentation Standards", "file_type": "document", "source_file": "src/lib/ai/knowledge/README.md", "source_location": "L25"}, {"id": "knowledge_readme_current_status", "label": "Current Status", "file_type": "document", "source_file": "src/lib/ai/knowledge/README.md", "source_location": "L32"}, {"id": "knowledge_readme_phase_1_foundation_complete", "label": "Phase 1: Foundation (Complete \u2705)", "file_type": "document", "source_file": "src/lib/ai/knowledge/README.md", "source_location": "L34"}, {"id": "knowledge_readme_phase_2_essential_modules_in_progress", "label": "Phase 2: Essential Modules (In Progress \ud83d\udea7)", "file_type": "document", "source_file": "src/lib/ai/knowledge/README.md", "source_location": "L40"}, {"id": "knowledge_readme_contributing_guidelines", "label": "Contributing Guidelines", "file_type": "document", "source_file": "src/lib/ai/knowledge/README.md", "source_location": "L46"}, {"id": "knowledge_readme_integration_points", "label": "Integration Points", "file_type": "document", "source_file": "src/lib/ai/knowledge/README.md", "source_location": "L54"}, {"id": "knowledge_readme_maintenance_schedule", "label": "Maintenance Schedule", "file_type": "document", "source_file": "src/lib/ai/knowledge/README.md", "source_location": "L61"}], "edges": [{"source": "d_proyect_opttius_app_src_lib_ai_knowledge_readme_md", "target": "knowledge_readme_ai_knowledge_base_index", "relation": "contains", "confidence": "EXTRACTED", "source_file": "src/lib/ai/knowledge/README.md", "source_location": "L1", "weight": 1.0}, {"source": "knowledge_readme_ai_knowledge_base_index", "target": "knowledge_readme_structure_overview", "relation": "contains", "confidence": "EXTRACTED", "source_file": "src/lib/ai/knowledge/README.md", "source_location": "L5", "weight": 1.0}, {"source": "knowledge_readme_ai_knowledge_base_index", "target": "knowledge_readme_documentation_standards", "relation": "contains", "confidence": "EXTRACTED", "source_file": "src/lib/ai/knowledge/README.md", "source_location": "L25", "weight": 1.0}, {"source": "knowledge_readme_ai_knowledge_base_index", "target": "knowledge_readme_current_status", "relation": "contains", "confidence": "EXTRACTED", "source_file": "src/lib/ai/knowledge/README.md", "source_location": "L32", "weight": 1.0}, {"source": "knowledge_readme_current_status", "target": "knowledge_readme_phase_1_foundation_complete", "relation": "contains", "confidence": "EXTRACTED", "source_file": "src/lib/ai/knowledge/README.md", "source_location": "L34", "weight": 1.0}, {"source": "knowledge_readme_current_status", "target": "knowledge_readme_phase_2_essential_modules_in_progress", "relation": "contains", "confidence": "EXTRACTED", "source_file": "src/lib/ai/knowledge/README.md", "source_location": "L40", "weight": 1.0}, {"source": "knowledge_readme_ai_knowledge_base_index", "target": "knowledge_readme_contributing_guidelines", "relation": "contains", "confidence": "EXTRACTED", "source_file": "src/lib/ai/knowledge/README.md", "source_location": "L46", "weight": 1.0}, {"source": "knowledge_readme_ai_knowledge_base_index", "target": "knowledge_readme_integration_points", "relation": "contains", "confidence": "EXTRACTED", "source_file": "src/lib/ai/knowledge/README.md", "source_location": "L54", "weight": 1.0}, {"source": "knowledge_readme_ai_knowledge_base_index", "target": "knowledge_readme_maintenance_schedule", "relation": "contains", "confidence": "EXTRACTED", "source_file": "src/lib/ai/knowledge/README.md", "source_location": "L61", "weight": 1.0}], "input_tokens": 0, "output_tokens": 0}